remarcableclient/__init__.py
remarcableclient/auth.py
remarcableclient/client.py
remarcableclient/config.py
remarcableclient/utils.py
remarcableclient/resources/assets.py
remarcableclient/resources/invoices.py
remarcableclient/resources/orders.py
remarcableclient/resources/price_files.py
remarcableclient/resources/projects.py
remarcableclient/resources/users.py
remarcableclient/resources/vendors.py
remarcableclient-1.0.0.dist-info/METADATA
remarcableclient-1.0.0.dist-info/WHEEL
remarcableclient-1.0.0.dist-info/top_level.txt
remarcableclient-1.0.0.dist-info/RECORD
