Metadata-Version: 2.4
Name: remarcableclient
Version: 1.0.0
Summary: Interacts with Remarcable's API to support inventory management
Author-email: Jacob Selbo <selbo.a.jacob@gmail.com>
Classifier: Development Status :: 5 - Production/Stable
Classifier: Intended Audience :: Developers
Requires-Python: >=3.10
Requires-Dist: pandas>=2.3.0
Requires-Dist: requests>=2.32.4
